{
  "slug": "2026-03-18-signature-aviation-unveils-new-glasgow-airport-fbo",
  "title": "Signature Aviation Unveils New Glasgow Airport Fbo",
  "wordCount": 29,
  "sections": [
    {
      "heading": "Summary",
      "content": "Signature Aviation Unveils New Glasgow Airport FBO. Signature Aviation has unveiled the latest in its facility modernization efforts with the grand opening yesterday of a new FBO terminal at..."
    }
  ],
  "images": [],
  "sourceReferences": [
    {
      "sourceId": "serper-scottish-aviation",
      "sourceUrl": "https://www.ainonline.com/aviation-news/business-aviation/2026-03-17/signature-aviation-unveils-new-glasgow-airport-fbo",
      "citationText": "serper-scottish-aviation – Signature Aviation Unveils New Glasgow Airport FBO"
    }
  ],
  "relatedBooks": [
    {
      "bookId": "clydeside-aviation-vol2",
      "reason": "Related research volume"
    }
  ],
  "keywords": [
    {
      "keyword": "Scottish aviation news",
      "primary": true
    },
    {
      "keyword": "aviation news",
      "primary": false
    },
    {
      "keyword": "MOD",
      "primary": false
    },
    {
      "keyword": "airport",
      "primary": false
    },
    {
      "keyword": "aviation",
      "primary": false
    },
    {
      "keyword": "Signature Aviation Unveils New",
      "primary": false
    }
  ],
  "status": "published",
  "createdAt": "2026-03-18T01:20:26.837Z"
}
