{
  "slug": "2026-03-18-glasgow-prestwick-air-cargo-link-to-china-ramped-u",
  "title": "Glasgow Prestwick Air Cargo Link To China Ramped U",
  "wordCount": 28,
  "sections": [
    {
      "heading": "Summary",
      "content": "Glasgow Prestwick air cargo link to China ramped up. Glasgow Prestwick Airport has announced that Air China Cargo has increased its cargo service between Prestwick and Chengdu Shuangliu..."
    }
  ],
  "images": [],
  "sourceReferences": [
    {
      "sourceId": "serper-scottish-aviation",
      "sourceUrl": "https://www.heraldscotland.com/news/25944138.air-china-cargo-increases-prestwick-service-daily-flights/",
      "citationText": "serper-scottish-aviation – Glasgow Prestwick air cargo link to China ramped up"
    }
  ],
  "relatedBooks": [
    {
      "bookId": "clydeside-aviation-vol2",
      "reason": "Related research volume"
    }
  ],
  "keywords": [
    {
      "keyword": "Scottish aviation news",
      "primary": true
    },
    {
      "keyword": "aviation news",
      "primary": false
    },
    {
      "keyword": "Prestwick",
      "primary": false
    },
    {
      "keyword": "airport",
      "primary": false
    },
    {
      "keyword": "Glasgow Prestwick Air Cargo",
      "primary": false
    }
  ],
  "status": "published",
  "createdAt": "2026-03-18T01:20:26.837Z"
}
