{
  "slug": "2026-03-12-prestwick-airport-marks-sixth-consecutive-profitab",
  "title": "Prestwick Airport marks sixth consecutive profitable year",
  "wordCount": 29,
  "sections": [
    {
      "heading": "Summary",
      "content": "Prestwick Airport marks sixth consecutive profitable year. Prestwick Airport has its sixth consecutive year of profit and an increase in its cargo operations, driven by e-commerce flights from China."
    }
  ],
  "images": [],
  "sourceReferences": [
    {
      "sourceId": "serper-scottish-aviation",
      "sourceUrl": "https://travelradar.aero/prestwick-airport-profit/",
      "citationText": "serper-scottish-aviation – Prestwick Airport marks sixth consecutive profitable year"
    }
  ],
  "relatedBooks": [
    {
      "bookId": "clydeside-aviation-vol2",
      "reason": "Related research volume"
    }
  ],
  "keywords": [
    {
      "keyword": "Scottish aviation news",
      "primary": true
    },
    {
      "keyword": "aviation news",
      "primary": false
    },
    {
      "keyword": "Prestwick",
      "primary": false
    },
    {
      "keyword": "airport",
      "primary": false
    },
    {
      "keyword": "Prestwick Airport marks sixth",
      "primary": false
    }
  ],
  "status": "published",
  "createdAt": "2026-03-12T12:38:07.481Z"
}
